wavespec/Globals.py
wavespec/Tests.py
wavespec/_CheckFirstImport.py
wavespec/__init__.py
wavespec/CrossPhase/CrossPhase.py
wavespec/CrossPhase/__init__.py
wavespec/CrossSpec/CrossSpec.py
wavespec/CrossSpec/SpectrogramFFT.py
wavespec/CrossSpec/SpectrogramLS.py
wavespec/CrossSpec/__init__.py
wavespec/DetectWaves/CPWaves.py
wavespec/DetectWaves/CombineWaves.py
wavespec/DetectWaves/DetectWavePeaks.py
wavespec/DetectWaves/__init__.py
wavespec/Filter/Filter.py
wavespec/Filter/IFilter.py
wavespec/Filter/Lanczos.py
wavespec/Filter/_CFunctions.py
wavespec/Filter/__init__.py
wavespec/Fourier/FFT.py
wavespec/Fourier/PlotSpectrogram.py
wavespec/Fourier/Spectrogram.py
wavespec/Fourier/Spectrogram3D.py
wavespec/Fourier/_GetFFTWindows.py
wavespec/Fourier/__init__.py
wavespec/LombScargle/InverseLombScargle.py
wavespec/LombScargle/LombScargle.py
wavespec/LombScargle/PlotSpectrogram.py
wavespec/LombScargle/Spectrogram.py
wavespec/LombScargle/Spectrogram3D.py
wavespec/LombScargle/_CFunctions.py
wavespec/LombScargle/_GetLSWindows.py
wavespec/LombScargle/__init__.py
wavespec/PCA/PCA.py
wavespec/PCA/__init__.py
wavespec/Spectrogram/DetectGaps.py
wavespec/Spectrogram/GetWindows.py
wavespec/Spectrogram/PlotSpectrogram.py
wavespec/Spectrogram/PlotSpectrogramOld.py
wavespec/Spectrogram/Spectrogram.py
wavespec/Spectrogram/Spectrogram3D.py
wavespec/Spectrogram/Spectrogram3DOld.py
wavespec/Spectrogram/SpectrogramOld.py
wavespec/Spectrogram/SpectrogramPlotter.py
wavespec/Spectrogram/__init__.py
wavespec/Test/FFT.py
wavespec/Test/LS.py
wavespec/Test/LSOversample.py
wavespec/Test/TestCP.py
wavespec/Test/TestCPEigenfreqs.py
wavespec/Test/TestCPSpectrogram.py
wavespec/Test/TestLS.py
wavespec/Test/TestPolarization.py
wavespec/Test/TestSpectrogram.py
wavespec/Test/__init__.py
wavespec/Tools/ArrowLine.py
wavespec/Tools/DetectGaps.py
wavespec/Tools/GetWindows.py
wavespec/Tools/PlotPolarization.py
wavespec/Tools/PolArrow.py
wavespec/Tools/Polarization2D.py
wavespec/Tools/PolyDetrend.py
wavespec-0.0.5.dist-info/LICENSE
wavespec-0.0.5.dist-info/METADATA
wavespec-0.0.5.dist-info/WHEEL
wavespec-0.0.5.dist-info/top_level.txt
wavespec-0.0.5.dist-info/RECORD
