Metadata-Version: 2.1
Name: wavespec
Version: 0.0.5
Summary: Some spectral analysis tools for analyzing waves in data.
Home-page: https://github.com/mattkjames7/wavespec
Author: Matthew Knight James
Author-email: mattkjames7@gmail.com
License: UNKNOWN
Platform: UNKNOWN
Classifier: Programming Language :: Python :: 3
Classifier: License :: OSI Approved :: GNU General Public License (GPL)
Classifier: Operating System :: POSIX
License-File: LICENSE
Requires-Dist: numpy
Requires-Dist: matplotlib
Requires-Dist: scipy
Requires-Dist: DateTimeTools
